kegstandcli/__init__.py
kegstandcli/utils.py
kegstandcli/version.py
kegstandcli/cli/__init__.py
kegstandcli/cli/__main__.py
kegstandcli/cli/build.py
kegstandcli/cli/config.py
kegstandcli/cli/default_lambda.py.tmpl
kegstandcli/cli/deploy.py
kegstandcli/cli/new.py
kegstandcli/cli/rest_api_gateway_health_check.py.tmpl
kegstandcli/cli/teardown.py
kegstandcli/infra/__init__.py
kegstandcli/infra/app.py
kegstandcli/infra/cdk.json
kegstandcli/infra/stacks/__init__.py
kegstandcli/infra/stacks/rest_api_backend.py
kegstandcli/infra/stacks/rest_api_gateway.py
kegstandcli-0.4.3.dist-info/METADATA
kegstandcli-0.4.3.dist-info/WHEEL
kegstandcli-0.4.3.dist-info/entry_points.txt
kegstandcli-0.4.3.dist-info/licenses/LICENSE
kegstandcli-0.4.3.dist-info/RECORD
