Metadata-Version: 2.4
Name: kegstandcli
Version: 0.4.3
Summary: The Developer's Toolbelt For Accelerating Mean-Time-To-Party on AWS
Project-URL: Homepage, https://kegstand.dev
Project-URL: Repository, https://github.com/jensroland/kegstand
Author-email: JensRoland <mail@jensroland.com>
License: MIT
License-File: LICENSE
Classifier: Development Status :: 4 - Beta
Classifier: Intended Audience :: Developers
Classifier: License :: OSI Approved :: MIT License
Classifier: Operating System :: OS Independent
Classifier: Programming Language :: Python :: 3
Classifier: Programming Language :: Python :: 3.10
Classifier: Programming Language :: Python :: 3.11
Classifier: Programming Language :: Python :: 3.12
Classifier: Programming Language :: Python :: 3.13
Classifier: Topic :: Software Development :: Libraries :: Python Modules
Requires-Python: >=3.10
Requires-Dist: aws-cdk-lib>=2.67.0
Requires-Dist: aws-solutions-constructs-aws-apigateway-lambda>=2.39.0
Requires-Dist: boto3>=1.17.113
Requires-Dist: click>=8.0.3
Requires-Dist: constructs<11.0.0,>=10.0.0
Requires-Dist: copier>=9.4.1
Requires-Dist: directory-tree>=1.0.0
Requires-Dist: pyjwt>=2.1.0
Requires-Dist: tomlkit>=0.11.7
Requires-Dist: xxhash>=3.2.0
